{
  "virtual_id":-1,
  "contentDescription":"",
  "rectangle":{
    "left_top_x":96,
    "left_top_y":0,
    "right_bottom_x":1824,
    "right_bottom_y":1026
  },
  "class_name":"android.widget.LinearLayout",
  "children":[
    {
      "virtual_id":0,
      "contentDescription":"Category Zero",
      "rectangle":{
        "left_top_x":96,
        "left_top_y":74,
        "right_bottom_x":349,
        "right_bottom_y":112
      },
      "class_name": "android.widget.TextView",
      "children":[
        {
          "contentDescription":"Movie I",
          "rectangle":{
            "left_top_x":96,
            "left_top_y":134,
            "right_bottom_x":404,
            "right_bottom_y":310
          },
          "class_name": "android.widget.ImageView",
          "children":[],
          "virtual_id":1
        },
        {
          "contentDescription":"Movie II",
          "rectangle":{
            "left_top_x":424,
            "left_top_y":134,
            "right_bottom_x":732,
            "right_bottom_y":310
          },
          "class_name": "android.widget.ImageView",
          "children":[],
          "virtual_id":2
        },
        {
          "contentDescription":"Movie III",
          "rectangle":{
            "left_top_x":752,
            "left_top_y":134,
            "right_bottom_x":1060,
            "right_bottom_y":310
          },
          "class_name": "android.widget.ImageView",
          "children":[],
          "virtual_id":3
        },
        {
          "contentDescription":"Movie IV",
          "rectangle":{
            "left_top_x":1080,
            "left_top_y":134,
            "right_bottom_x":1388,
            "right_bottom_y":310
          },
          "class_name": "android.widget.ImageView",
          "children":[],
          "virtual_id":4
        },
        {
          "contentDescription":"Movie V",
          "rectangle":{
            "left_top_x":1408,
            "left_top_y":134,
            "right_bottom_x":1716,
            "right_bottom_y":310
          },
          "class_name": "android.widget.ImageView",
          "children":[],
          "virtual_id":5
        },
        {
          "contentDescription":"Movie VI",
          "rectangle":{
            "left_top_x":1736,
            "left_top_y":134,
            "right_bottom_x":1824,
            "right_bottom_y":310
          },
          "class_name": "android.widget.ImageView",
          "children":[],
          "virtual_id":6
        }
      ]
    },
    {
      "virtual_id":7,
      "contentDescription":"Category One",
      "rectangle":{
        "left_top_x":96,
        "left_top_y":360,
        "right_bottom_x":338,
        "right_bottom_y":398
      },
      "class_name": "android.widget.TextView",
      "children":[
        {
          "contentDescription":"Movie I",
          "rectangle":{
            "left_top_x":96,
            "left_top_y":420,
            "right_bottom_x":404,
            "right_bottom_y":596
          },
          "class_name": "android.widget.ImageView",
          "children":[],
          "virtual_id":8
        },
        {
          "contentDescription":"Movie II",
          "rectangle":{
            "left_top_x":424,
            "left_top_y":420,
            "right_bottom_x":732,
            "right_bottom_y":596
          },
          "class_name": "android.widget.ImageView",
          "children":[],
          "virtual_id":9
        },
        {
          "contentDescription":"Movie III",
          "rectangle":{
            "left_top_x":752,
            "left_top_y":420,
            "right_bottom_x":1060,
            "right_bottom_y":596
          },
          "class_name": "android.widget.ImageView",
          "children":[],
          "virtual_id":10
        },
        {
          "contentDescription":"Movie IV",
          "rectangle":{
            "left_top_x":1080,
            "left_top_y":420,
            "right_bottom_x":1388,
            "right_bottom_y":596
          },
          "class_name": "android.widget.ImageView",
          "children":[],
          "virtual_id":11
        },
        {
          "contentDescription":"Movie V",
          "rectangle":{
            "left_top_x":1408,
            "left_top_y":420,
            "right_bottom_x":1716,
            "right_bottom_y":596
          },
          "class_name": "android.widget.ImageView",
          "children":[],
          "virtual_id":12
        },
        {
          "contentDescription":"Movie VI",
          "rectangle":{
            "left_top_x":1736,
            "left_top_y":420,
            "right_bottom_x":1824,
            "right_bottom_y":596
          },
          "class_name": "android.widget.ImageView",
          "children":[],
          "virtual_id":13
        }
      ]
    },
    {
      "virtual_id":14,
      "contentDescription":"Category Two",
      "rectangle":{
        "left_top_x":96,
        "left_top_y":646,
        "right_bottom_x":343,
        "right_bottom_y":684
      },
      "class_name": "android.widget.TextView",
      "children":[
        {
          "contentDescription":"Movie I",
          "rectangle":{
            "left_top_x":96,
            "left_top_y":706,
            "right_bottom_x":404,
            "right_bottom_y":882
          },
          "class_name": "android.widget.ImageView",
          "children":[],
          "virtual_id":15
        },
        {
          "contentDescription":"Movie II",
          "rectangle":{
            "left_top_x":424,
            "left_top_y":706,
            "right_bottom_x":732,
            "right_bottom_y":882
          },
          "class_name": "android.widget.ImageView",
          "children":[],
          "virtual_id":16
        },
        {
          "contentDescription":"Movie III",
          "rectangle":{
            "left_top_x":752,
            "left_top_y":706,
            "right_bottom_x":1060,
            "right_bottom_y":882
          },
          "class_name": "android.widget.ImageView",
          "children":[],
          "virtual_id":17
        },
        {
          "contentDescription":"Movie IV",
          "rectangle":{
            "left_top_x":1080,
            "left_top_y":706,
            "right_bottom_x":1388,
            "right_bottom_y":882
          },
          "class_name": "android.widget.ImageView",
          "children":[],
          "virtual_id":18
        },
        {
          "contentDescription":"Movie V",
          "rectangle":{
            "left_top_x":1408,
            "left_top_y":706,
            "right_bottom_x":1716,
            "right_bottom_y":882
          },
          "class_name": "android.widget.ImageView",
          "children":[],
          "virtual_id":19
        },
        {
          "contentDescription":"Movie VI",
          "rectangle":{
            "left_top_x":1736,
            "left_top_y":706,
            "right_bottom_x":1824,
            "right_bottom_y":882
          },
          "class_name": "android.widget.ImageView",
          "children":[],
          "virtual_id":20
        }
      ]
    },
    {
      "virtual_id":21,
      "contentDescription":"Category Three",
      "rectangle":{
        "left_top_x":96,
        "left_top_y":931,
        "right_bottom_x":369,
        "right_bottom_y":970
      },
      "class_name": "android.widget.TextView",
      "children":[
        {
          "contentDescription":"Movie I",
          "rectangle":{
            "left_top_x":96,
            "left_top_y":992,
            "right_bottom_x":404,
            "right_bottom_y":1026
          },
          "class_name": "android.widget.ImageView",
          "children":[],
          "virtual_id":22
        },
        {
          "contentDescription":"Movie II",
          "rectangle":{
            "left_top_x":424,
            "left_top_y":992,
            "right_bottom_x":732,
            "right_bottom_y":1026
          },
          "class_name": "android.widget.ImageView",
          "children":[],
          "virtual_id":23
        },
        {
          "contentDescription":"Movie III",
          "rectangle":{
            "left_top_x":752,
            "left_top_y":992,
            "right_bottom_x":1060,
            "right_bottom_y":1026
          },
          "class_name": "android.widget.ImageView",
          "children":[],
          "virtual_id":24
        },
        {
          "contentDescription":"Movie IV",
          "rectangle":{
            "left_top_x":1080,
            "left_top_y":992,
            "right_bottom_x":1388,
            "right_bottom_y":1026
          },
          "class_name": "android.widget.ImageView",
          "children":[],
          "virtual_id":25
        },
        {
          "contentDescription":"Movie V",
          "rectangle":{
            "left_top_x":1408,
            "left_top_y":992,
            "right_bottom_x":1716,
            "right_bottom_y":1026
          },
          "class_name": "android.widget.ImageView",
          "children":[],
          "virtual_id":26
        },
        {
          "contentDescription":"Movie VI",
          "rectangle":{
            "left_top_x":1736,
            "left_top_y":992,
            "right_bottom_x":1824,
            "right_bottom_y":1026
          },
          "class_name": "android.widget.ImageView",
          "children":[],
          "virtual_id":27
        }
      ]
    }
  ]
}